{
  "name": "wind",
  "tag": "wind",
  "version": 1,
  "flags": 2,
  "block": "wind_block",
  "blocks": {
    "wind_block": {
      "max_count": 1,
      "max_count_string": "1",
      "struct": "wind_block"
    }
  },
  "structs": {
    "wind_block": {
      "guid": "75d2544f454503398cdd99a0c27b64b8",
      "size": 120,
      "size_string": "sizeof(s_wind_definition)",
      "flags": 44,
      "fields": [
        {
          "type": "explanation",
          "name": "WIND DIRECTION",
          "definition": "Speed is in MPH, direction is in degrees:\n   0\u00b0  North\n  90\u00b0  East\n 180\u00b0  South\n 270\u00b0  West\n"
        },
        {
          "type": "struct",
          "name": "direction",
          "definition": "wind_scalar_function_struct"
        },
        {
          "type": "struct",
          "name": "speed",
          "definition": "wind_scalar_function_struct"
        },
        {
          "type": "explanation",
          "name": "DECORATOR WIND MOTION",
          "definition": "These are all a function of the wind speed (between 0 MPH on the left and 200 MPH on the right)\n\nbend: how much the decorators bend - 0.0 is standing straight up, 10.0 is super-flattened\noscillation: how much the decorators 'oscillate' at a given speed\nfrequency: how fast the oscillation waves each decorator\ngust size: big gusts move large areas of decorators in sync.  small gusts give more variation\n"
        },
        {
          "type": "struct",
          "name": "bend",
          "definition": "wind_scalar_function_struct"
        },
        {
          "type": "struct",
          "name": "oscillation",
          "definition": "wind_scalar_function_struct"
        },
        {
          "type": "struct",
          "name": "frequency",
          "definition": "wind_scalar_function_struct"
        },
        {
          "type": "real",
          "name": "gust size:world units"
        },
        {
          "type": "tag_reference",
          "name": "gust noise bitmap",
          "definition": {
            "flags": 0,
            "allowed": [
              "bitm"
            ]
          }
        },
        {
          "type": "terminator",
          "name": null
        }
      ],
      "source_file": "c:\\mcc\\release\\h3\\source\\scenario\\wind_definitions.cpp"
    },
    "wind_scalar_function_struct": {
      "guid": "f7779fc15e4be7bd8f59baa428a38f19",
      "size": 20,
      "size_string": "sizeof(s_wind_function)",
      "flags": 27,
      "fields": [
        {
          "type": "custom",
          "name": "Mapping",
          "group_tag": "fned",
          "definition": "Cq?0"
        },
        {
          "type": "struct",
          "name": "Mapping",
          "definition": "mapping_function"
        },
        {
          "type": "terminator",
          "name": null
        }
      ],
      "source_file": "c:\\mcc\\release\\h3\\source\\scenario\\wind_definitions.cpp"
    },
    "mapping_function": {
      "guid": "8fa9145a8444fa53d46810809e45f10a",
      "size": 20,
      "size_string": "actual_size",
      "flags": 6999,
      "fields": [
        {
          "type": "custom",
          "name": null,
          "group_tag": "hide"
        },
        {
          "type": "data",
          "name": "data",
          "definition": "function_definition_data"
        },
        {
          "type": "custom",
          "name": null,
          "group_tag": "edih"
        },
        {
          "type": "terminator",
          "name": null
        }
      ],
      "source_file": "c:\\mcc\\release\\h3\\source\\math\\function_definitions.cpp"
    }
  },
  "datas": {
    "function_definition_data": {
      "alignment": 4,
      "flags": 2,
      "max_size": 872,
      "max_size_string": "k_max_function_size"
    }
  }
}