{
 "name": "flag",
 "tag": "flag",
 "version": 1,
 "flags": 0,
 "block": "flag_block",
 "blocks": {
  "flag_block": {
   "max_count": 1,
   "max_count_string": "1",
   "struct": "flag_block_struct"
  },
  "attachment_points_block": {
   "max_count": 5,
   "max_count_string": "5",
   "struct": "attachment_points_block_struct"
  }
 },
 "structs": {
  "flag_block_struct": {
   "guid": "00000000000000000000000000000000",
   "size": 96,
   "fields": [
    {
     "type": "long_flags",
     "name": "flags",
     "definition": "flags_flags"
    },
    {
     "type": "short_enum",
     "name": "trailing edge shape",
     "definition": "trailing_edge_shape_enum"
    },
    {
     "type": "short_integer",
     "name": "trailing edge shape offset"
    },
    {
     "type": "short_enum",
     "name": "attached edge shape",
     "definition": "attached_edge_shape_enum"
    },
    {
     "type": "pad",
     "name": "pad",
     "definition": 2
    },
    {
     "type": "short_integer",
     "name": "width"
    },
    {
     "type": "short_integer",
     "name": "height"
    },
    {
     "type": "real",
     "name": "cell width"
    },
    {
     "type": "real",
     "name": "cell height"
    },
    {
     "type": "tag_reference",
     "name": "red flag shader"
    },
    {
     "type": "tag_reference",
     "name": "physics"
    },
    {
     "type": "real",
     "name": "wind noise"
    },
    {
     "type": "pad",
     "name": "pad",
     "definition": 8
    },
    {
     "type": "tag_reference",
     "name": "blue flag shader"
    },
    {
     "type": "block",
     "name": "attachment points",
     "definition": "attachment_points_block"
    },
    {
     "type": "terminator",
     "name": null
    }
   ]
  },
  "attachment_points_block_struct": {
   "guid": "00000000000000000000000000000000",
   "size": 52,
   "fields": [
    {
     "type": "short_integer",
     "name": "height to next attachment"
    },
    {
     "type": "pad",
     "name": "pad",
     "definition": 2
    },
    {
     "type": "pad",
     "name": "pad",
     "definition": 16
    },
    {
     "type": "string",
     "name": "marker name"
    },
    {
     "type": "terminator",
     "name": null
    }
   ]
  }
 },
 "arrays": {},
 "enums_flags": {
  "flags_flags": {
   "options": [
    "unused"
   ]
  },
  "trailing_edge_shape_enum": {
   "options": [
    "flat",
    "concave triangular",
    "convex triangular",
    "trapezoid short top",
    "trapezoid short bottom"
   ]
  },
  "attached_edge_shape_enum": {
   "options": [
    "flat",
    "concave triangular"
   ]
  }
 },
 "datas": {},
 "resources": {},
 "interops": {}
}