{
  "name": "meter",
  "tag": "metr",
  "version": 1,
  "flags": 2,
  "block": "meter_block",
  "blocks": {
    "meter_block": {
      "max_count": 1,
      "max_count_string": "1",
      "struct": "meter_struct_definition"
    }
  },
  "structs": {
    "meter_struct_definition": {
      "guid": "fbaa483bfc47c1f0069e43ad9a74afed",
      "size": 172,
      "size_string": "sizeof(struct meter_definition)",
      "flags": 58,
      "fields": [
        {
          "type": "long_flags",
          "name": "flags",
          "definition": "meter_flags"
        },
        {
          "type": "tag_reference",
          "name": "stencil bitmaps#two bitmaps specifying the mask and the meter levels",
          "definition": {
            "flags": 2,
            "allowed": [
              "bitm"
            ]
          }
        },
        {
          "type": "tag_reference",
          "name": "source bitmap#optional bitmap to draw into the unmasked regions of the meter (modulated by the colors below)",
          "definition": {
            "flags": 0,
            "allowed": [
              "bitm"
            ]
          }
        },
        {
          "type": "short_integer",
          "name": "stencil sequence index"
        },
        {
          "type": "short_integer",
          "name": "source sequence index"
        },
        {
          "type": "pad",
          "name": "KBT",
          "definition": 16
        },
        {
          "type": "pad",
          "name": "ON",
          "definition": 4
        },
        {
          "type": "short_enum",
          "name": "interpolate colors...",
          "definition": "color_interpolation_modes_enum"
        },
        {
          "type": "short_enum",
          "name": "anchor colors...",
          "definition": "color_anchors_enum"
        },
        {
          "type": "pad",
          "name": "WMTT",
          "definition": 8
        },
        {
          "type": "real_argb_color",
          "name": "empty color"
        },
        {
          "type": "real_argb_color",
          "name": "full color"
        },
        {
          "type": "pad",
          "name": "VNJW",
          "definition": 20
        },
        {
          "type": "real",
          "name": "unmask distance:meter units#fade from fully masked to fully unmasked this distance beyond full (and below empty)"
        },
        {
          "type": "real",
          "name": "mask distance:meter units#fade from fully unmasked to fully masked this distance below full (and beyond empty)"
        },
        {
          "type": "pad",
          "name": "SBQWDR",
          "definition": 20
        },
        {
          "type": "data",
          "name": "encoded stencil",
          "definition": "meter_stencil_data_definition"
        },
        {
          "type": "terminator",
          "name": null
        }
      ],
      "source_file": "c:\\mcc\\qfe1\\reach\\shared\\engine\\source\\omaha\\interface\\meter_definitions.cpp"
    }
  },
  "enums_flags": {
    "meter_flags": {
      "options": [],
      "source_file": "c:\\mcc\\qfe1\\reach\\shared\\engine\\source\\omaha\\interface\\meter_definitions.cpp"
    },
    "color_interpolation_modes_enum": {
      "options": [
        "linearly",
        "faster near empty",
        "faster near full",
        "through random noise"
      ],
      "source_file": "c:\\mcc\\qfe1\\reach\\shared\\engine\\source\\omaha\\interface\\meter_definitions.cpp"
    },
    "color_anchors_enum": {
      "options": [
        "at both ends",
        "at empty",
        "at full"
      ],
      "source_file": "c:\\mcc\\qfe1\\reach\\shared\\engine\\source\\omaha\\interface\\meter_definitions.cpp"
    }
  },
  "datas": {
    "meter_stencil_data_definition": {
      "alignment": 0,
      "flags": 0,
      "max_size": 65536,
      "max_size_string": "MAXIMUM_METER_DEFINITION_ENCODED_STENCIL_SIZE"
    }
  }
}